pyrabbitmq/__init__.py
pyrabbitmq/connection.py
pyrabbitmq-0.0.4.dist-info/METADATA
pyrabbitmq-0.0.4.dist-info/WHEEL
pyrabbitmq-0.0.4.dist-info/top_level.txt
pyrabbitmq-0.0.4.dist-info/RECORD
