Metadata-Version: 2.1
Name: pyrabbitmq
Version: 0.0.4
Summary: Simple Python client library for RabbitMQ
Home-page: https://github.com/xizhendu/pyrabbitmq
Author: Xizhen Du
Author-email: xizhendu@gmail.com
Requires-Dist: requests
